cloverpy/__init__.py
cloverpy/clover.py
cloverpy-0.1.1.dist-info/DESCRIPTION.rst
cloverpy-0.1.1.dist-info/METADATA
cloverpy-0.1.1.dist-info/RECORD
cloverpy-0.1.1.dist-info/WHEEL
cloverpy-0.1.1.dist-info/entry_points.txt
cloverpy-0.1.1.dist-info/metadata.json
cloverpy-0.1.1.dist-info/top_level.txt
