Metadata-Version: 2.0
Name: cloverpy
Version: 0.1.1
Summary: Utility to convert coverage.py's coverage.xml to clover.xml without any 3rd party dependencies.
Home-page: UNKNOWN
Author: Digicat
Author-email: UNKNOWN
License: UNKNOWN
Platform: UNKNOWN
